BERTeam/__init__.py
BERTeam/buffer/__init__.py
BERTeam/buffer/language_replay_buffer.py
BERTeam/networks/__init__.py
BERTeam/networks/input_embedding.py
BERTeam/networks/positional_encoder.py
BERTeam/networks/team_builder.py
BERTeam/outcome/__init__.py
BERTeam/outcome/game_outcome.py
BERTeam/tests/L1_best_response.py
BERTeam/tests/rps_basic/game.py
BERTeam/tests/rps_basic/teams.py
BERTeam/tests/rps_dual/game.py
BERTeam/tests/rps_dual/teams.py
BERTeam/trainer/__init__.py
BERTeam/trainer/team_trainer.py
BERTeam/utility/__init__.py
BERTeam/utility/sorted_list.py
berteam-0.0.1000000002169.dist-info/LICENSE
berteam-0.0.1000000002169.dist-info/METADATA
berteam-0.0.1000000002169.dist-info/WHEEL
berteam-0.0.1000000002169.dist-info/top_level.txt
berteam-0.0.1000000002169.dist-info/RECORD
